notion_news_crawler/__init__.py
notion_news_crawler/config.py
notion_news_crawler/naver_api.py
notion_news_crawler/reset_database.py
notion_news_crawler/upload_to_database.py
notion_news_crawler-0.0.9.dist-info/LICENSE
notion_news_crawler-0.0.9.dist-info/METADATA
notion_news_crawler-0.0.9.dist-info/WHEEL
notion_news_crawler-0.0.9.dist-info/top_level.txt
notion_news_crawler-0.0.9.dist-info/RECORD
