Metadata-Version: 2.1
Name: notion-news-crawler
Version: 0.0.9
Summary: Notion news mecro
Home-page: https://github.com/kar7mp5/Notion-News-Crawler.git
Author: MinSup Kim
Author-email: tommy1005a@gmail.com
License: UNKNOWN
Platform: UNKNOWN
License-File: LICENSE
Requires-Dist: python-dotenv
Requires-Dist: pytz
Requires-Dist: requests
Requires-Dist: retrying
Requires-Dist: selenium
Requires-Dist: tqdm
